{
    "_comment": "Clotho package.json 翻译 - 简体中文",
    "displayName": "Clotho - C/C++ clangd 增强工具",
    "description": "强大的 VS Code 扩展，增强 C/C++ 开发体验，集成 clangd 支持。",
    "command.newSourcePair.title": "新建 C/C++ 头文件/源文件对",
    "command.newSourcePair.category": "Clotho",
    "command.switchHeaderSource.title": "切换头文件/源文件",
    "command.switchHeaderSource.category": "Clotho",
    "command.configureRules.title": "配置 C++ 文件扩展名规则",
    "command.configureRules.category": "Clotho",
    "command.configureHeaderGuard.title": "配置头文件保护符风格",
    "command.configureHeaderGuard.category": "Clotho",
    "command.openClangFormatEditor.title": "打开 Clang-Format 可视化编辑器",
    "command.openClangFormatEditor.category": "Clotho",
    "command.qt.newProject.title": "新建 Qt CMake 项目",
    "command.clangFormat.validate.title": "校验 Clang-Format 配置",
    "command.clangFormat.rollbackLastSaved.title": "回滚到上一次保存的配置",
    "command.clangFormat.applyTextToPreview.title": "将 .clang-format 文本应用到预览（干跑）",
    "config.pairingRules.title": "文件扩展名配对规则",
    "config.pairingRules.description": "自定义头文件和源文件扩展名的配对规则。每条规则将头文件扩展名映射到源文件扩展名。",
    "config.headerGuard.title": "头文件保护符",
    "config.headerGuard.description": "C/C++ 头文件保护符配置。",
    "config.headerGuard.style.title": "头文件保护符风格",
    "config.headerGuard.style.description": "新建头文件时使用的头文件保护符风格。",
    "config.headerGuard.style.ifndef": "#ifndef/#define/#endif",
    "config.headerGuard.style.pragmaOnce": "#pragma once",
    "config.headerGuard.format.title": "头文件保护符格式",
    "config.headerGuard.format.description": "生成头文件保护符名称的格式字符串。可用占位符: {FILE_NAME}, {FILE_NAME_UPPER}, {FILE_PATH}, {PROJECT_NAME}",
    "config.clangFormat.title": "Clang-Format",
    "config.clangFormat.description": "clang-format 可视化编辑器配置。",
    "command.debug.dumpSwitchMetrics.title": "输出切换性能指标",
    "command.debug.selfTest.strategies.title": "运行策略自测",
    "command.debug.clearAllCaches.title": "清除所有缓存",
    "command.debug.dumpSwitchReport.title": "输出切换性能报告",
    "config.performance.slowOperationThreshold.description": "超过该毫秒阈值的操作会视为耗时较长",
    "config.fs.enableWatcher.description": "启用文件系统监听以便缓存失效",
    "config.fs.watchGlobs.description": "额外的监听通配符（RelativePattern），为空则使用默认值",
    "config.switch.cacheTTLms.description": "切换结果缓存的 TTL（毫秒，0 表示关闭）",
    "config.logLevel.description": "Clotho 日志的最低级别",
    "config.switch.ranking.sameDirBoost.description": "同目录候选的排序权重",
    "config.switch.ranking.includeSrcBoost.description": "include↔src 语义的排序权重",
    "config.switch.ranking.workspaceRootBoost.description": "同一工作区根目录候选的排序权重",
    "config.switch.ranking.extOrderBase.description": "按目标扩展顺序的基础加分",
    "config.switch.ranking.depthBonusBase.description": "路径层级距离的基础加分"
}